titan/__init__.py
titan/__main__.py
titan/api.py
titan/blueprint.py
titan/blueprint_config.py
titan/builder.py
titan/builtins.py
titan/cli.py
titan/client.py
titan/data_provider.py
titan/data_types.py
titan/enums.py
titan/exceptions.py
titan/gitops.py
titan/identifiers.py
titan/lifecycle.py
titan/parse.py
titan/parse_primitives.py
titan/policy.py
titan/privs.py
titan/props.py
titan/py.typed
titan/resource_name.py
titan/resource_tags.py
titan/role_ref.py
titan/scope.py
titan/sql.py
titan/var.py
titan/adapters/__init__.py
titan/adapters/permifrost.py
titan/adapters/py.typed
titan/operations/__init__.py
titan/operations/blueprint.py
titan/operations/connector.py
titan/operations/export.py
titan/resources/__init__.py
titan/resources/account.py
titan/resources/account_parameter.py
titan/resources/aggregation_policy.py
titan/resources/alert.py
titan/resources/api_integration.py
titan/resources/authentication_policy.py
titan/resources/catalog_integration.py
titan/resources/column.py
titan/resources/compute_pool.py
titan/resources/database.py
titan/resources/dynamic_table.py
titan/resources/event_table.py
titan/resources/external_access_integration.py
titan/resources/external_function.py
titan/resources/external_volume.py
titan/resources/failover_group.py
titan/resources/file_format.py
titan/resources/function.py
titan/resources/grant.py
titan/resources/hybrid_table.py
titan/resources/iceberg_table.py
titan/resources/image_repository.py
titan/resources/masking_policy.py
titan/resources/materialized_view.py
titan/resources/network_policy.py
titan/resources/network_rule.py
titan/resources/notebook.py
titan/resources/notification_integration.py
titan/resources/packages_policy.py
titan/resources/password_policy.py
titan/resources/pipe.py
titan/resources/procedure.py
titan/resources/py.typed
titan/resources/replication_group.py
titan/resources/resource.py
titan/resources/resource_monitor.py
titan/resources/role.py
titan/resources/scanner_package.py
titan/resources/schema.py
titan_core-0.11.1.dist-info/LICENSE
titan_core-0.11.1.dist-info/METADATA
titan_core-0.11.1.dist-info/WHEEL
titan_core-0.11.1.dist-info/entry_points.txt
titan_core-0.11.1.dist-info/top_level.txt
titan_core-0.11.1.dist-info/RECORD
