Metadata-Version: 2.1
Name: titan-core
Version: 0.11.1
Summary: Titan Core: Snowflake infrastructure as code
Home-page: https://github.com/Titan-Systems/titan
Author: TJ Murphy
Project-URL: Homepage, https://github.com/Titan-Systems/titan
Classifier: Development Status :: 4 - Beta
Classifier: License :: OSI Approved :: Apache Software License
Classifier: Intended Audience :: Developers
Classifier: Operating System :: OS Independent
Classifier: Programming Language :: Python :: 3 :: Only
Classifier: Programming Language :: SQL
Classifier: Topic :: Database
Requires-Python: >=3.9
License-File: LICENSE
Requires-Dist: click==8.1.7
Requires-Dist: inflection==0.5.1
Requires-Dist: pyparsing==3.0.9
Requires-Dist: pyyaml
Requires-Dist: snowflake-connector-python==3.12.3
Requires-Dist: snowflake-snowpark-python==1.24.0
Requires-Dist: pyOpenSSL>=22.1.0
Requires-Dist: jinja2
Requires-Dist: pathspec
Provides-Extra: dev
Requires-Dist: black; extra == "dev"
Requires-Dist: build; extra == "dev"
Requires-Dist: codespell==2.2.6; extra == "dev"
Requires-Dist: mypy; extra == "dev"
Requires-Dist: pytest-cov; extra == "dev"
Requires-Dist: pytest-profiling!=1.8.0; extra == "dev"
Requires-Dist: pytest-xdist; extra == "dev"
Requires-Dist: pytest>=6.0; extra == "dev"
Requires-Dist: python-dotenv; extra == "dev"
Requires-Dist: ruff; extra == "dev"
Requires-Dist: tabulate; extra == "dev"
Requires-Dist: twine!=5.1.0; extra == "dev"
Requires-Dist: types-pytz; extra == "dev"
Requires-Dist: types-pyyaml; extra == "dev"
